anthology/__init__.py
anthology/commands/__init__.py
anthology/commands/install.py
anthology/commands/run.py
anthology/commands/version.py
anthology/definitions/config.py
anthology/definitions/version_constraint_collection.py
anthology/definitions/version_constraint_container.py
anthology/main.py
anthology/plugin.py
anthology/utils.py
anthology-0.1.7.dist-info/LICENSE.md
anthology-0.1.7.dist-info/METADATA
anthology-0.1.7.dist-info/WHEEL
anthology-0.1.7.dist-info/entry_points.txt
anthology-0.1.7.dist-info/RECORD
