Metadata-Version: 2.1
Name: anthology
Version: 0.1.7
Summary: Python Poetry Monorepo Tooling
License: Apache-2.0
Author: Zack Clark-Kington
Author-email: zack@causalens.com
Requires-Python: >=3.8,<4.0
Classifier: License :: OSI Approved :: Apache Software License
Classifier: Programming Language :: Python :: 3
Classifier: Programming Language :: Python :: 3.8
Classifier: Programming Language :: Python :: 3.9
Classifier: Programming Language :: Python :: 3.10
Classifier: Programming Language :: Python :: 3.11
Classifier: Programming Language :: Python :: 3.12
Requires-Dist: cffi (>=1.17.1,<2.0.0)
Requires-Dist: cleo (>=2.1.0,<3.0.0)
Requires-Dist: click (>=8.1.7,<9.0.0)
Requires-Dist: poetry (>=1.8.2,<1.9.0)
Requires-Dist: poetry-core (>=1.9.0,<1.10.0)
Requires-Dist: pydantic (>=2.7.1,<3.0.0)
Requires-Dist: tomli (>=2.0.1,<3.0.0) ; python_version < "3.11"
